typeval/__init__.py
typeval/_constraints.py
typeval-0.1.0.dist-info/LICENSE.txt
typeval-0.1.0.dist-info/WHEEL
typeval-0.1.0.dist-info/METADATA
typeval-0.1.0.dist-info/RECORD
